aisak/__init__.py
aisak/aisak.py
aisak-2.3.1.dist-info/METADATA
aisak-2.3.1.dist-info/WHEEL
aisak-2.3.1.dist-info/top_level.txt
aisak-2.3.1.dist-info/RECORD
